probium/__init__.py
probium/__main__.py
probium/cache.py
probium/cli.py
probium/core.py
probium/detection_schema.json
probium/exceptions.py
probium/google_magika.py
probium/launcher.py
probium/libmagic.py
probium/logging_cfg.py
probium/magic_service.py
probium/models.py
probium/registry.py
probium/scoring.py
probium/trid_multi.py
probium/watch.py
probium/engines/__init__.py
probium/engines/base.py
probium/engines/bat.py
probium/engines/bmp.py
probium/engines/bzip2.py
probium/engines/cpp.py
probium/engines/csv.py
probium/engines/dockerfile.py
probium/engines/exe.py
probium/engines/fallback.py
probium/engines/gzip.py
probium/engines/html.py
probium/engines/ico.py
probium/engines/image.py
probium/engines/js.py
probium/engines/json.py
probium/engines/kotlin.py
probium/engines/legacy_office.py
probium/engines/magiclib.py
probium/engines/magika.py
probium/engines/makefile.py
probium/engines/mp3.py
probium/engines/mp4.py
probium/engines/ogg.py
probium/engines/pdf.py
probium/engines/png.py
probium/engines/powershell.py
probium/engines/python.py
probium/engines/rar.py
probium/engines/rust.py
probium/engines/sevenz.py
probium/engines/sh.py
probium/engines/signature.py
probium/engines/sqlite.py
probium/engines/swift.py
probium/engines/tar.py
probium/engines/text.py
probium/engines/wav.py
probium/engines/xml.py
probium/engines/xz.py
probium/engines/zip_office.py
probium/engines/textengines/__init__.py
probium/engines/textengines/bat.py
probium/engines/textengines/c.py
probium/engines/textengines/cpp.py
probium/engines/textengines/csv.py
probium/engines/textengines/java.py
probium/engines/textengines/javascript.py
probium/engines/textengines/json.py
probium/engines/textengines/makefile.py
probium/engines/textengines/python.py
probium/engines/textengines/rust.py
probium/engines/textengines/xml.py
probium/test_harness/__init__.py
probium/test_harness/unittest.py
probium-0.3.2.dist-info/METADATA
probium-0.3.2.dist-info/WHEEL
probium-0.3.2.dist-info/entry_points.txt
probium-0.3.2.dist-info/top_level.txt
probium-0.3.2.dist-info/RECORD
